<?xml version="1.0" encoding="UTF-8"?>
<feature
      id="org.jboss.tools.community.central.feature"
      label="%featureName"
      version="1.0.0.qualifier"
      provider-name="%providerName"
      plugin="org.jboss.tools.community.central">

   <description>
      %description
   </description>

   <copyright>
      %copyright
   </copyright>

   <license url="%licenseURL">
      %license
   </license>

   <requires>
      <import feature="org.jboss.tools.community.project.examples.feature" version="1.2.1.qualifier" match="greaterOrEqual"/>
   </requires>

   <plugin
         id="org.jboss.tools.community.central"
         download-size="0"
         install-size="0"
         version="0.0.0"/>

</feature>
